z3c/sqlalchemy/__init__.py
z3c/sqlalchemy/base.py
z3c/sqlalchemy/interfaces.py
z3c/sqlalchemy/mapper.py
z3c/sqlalchemy/model.py
z3c/sqlalchemy/postgres.py
z3c/sqlalchemy/util.py
z3c/sqlalchemy/tests/__init__.py
z3c/sqlalchemy/tests/test_SQLAlchemy.py
z3c_sqlalchemy-3.0.dist-info/LICENSE.txt
z3c_sqlalchemy-3.0.dist-info/METADATA
z3c_sqlalchemy-3.0.dist-info/WHEEL
z3c_sqlalchemy-3.0.dist-info/top_level.txt
z3c_sqlalchemy-3.0.dist-info/RECORD
