Metadata-Version: 2.2
Name: z3c.sqlalchemy
Version: 3.0
Summary: A SQLAlchemy wrapper for Zope
Home-page: https://github.com/zopefoundation/z3c.sqlalchemy
Author: Andreas Jung
Author-email: info@zopyx.com
Maintainer: Zope Foundation and Contributors
Maintainer-email: zope-dev@zope.dev
License: ZPL-2.1
Project-URL: Issue Tracker, https://github.com/zopefoundation/z3c.sqlalchemy/issues
Project-URL: Sources, https://github.com/zopefoundation/z3c.sqlalchemy
Classifier: Development Status :: 5 - Production/Stable
Classifier: Intended Audience :: Developers
Classifier: License :: OSI Approved :: Zope Public License
Classifier: Operating System :: OS Independent
Classifier: Framework :: Zope
Classifier: Framework :: Zope :: 3
Classifier: Framework :: Zope :: 4
Classifier: Framework :: Zope :: 5
Classifier: Programming Language :: Python
Classifier: Topic :: Database :: Front-Ends
Classifier: Topic :: Software Development :: Libraries :: Python Modules
Classifier: Programming Language :: Python :: 3.9
Classifier: Programming Language :: Python :: 3.10
Classifier: Programming Language :: Python :: 3.11
Classifier: Programming Language :: Python :: 3.12
Classifier: Programming Language :: Python :: 3.13
Requires-Python: >=3.9
License-File: LICENSE.txt
Requires-Dist: setuptools
Requires-Dist: SQLAlchemy>=1.4
Requires-Dist: zope.sqlalchemy>=1.2.0
Requires-Dist: zope.component
Requires-Dist: zope.interface
Requires-Dist: zope.testing
Requires-Dist: zope.schema
Provides-Extra: test
Requires-Dist: zope.testing; extra == "test"
Dynamic: author
Dynamic: author-email
Dynamic: classifier
Dynamic: description
Dynamic: home-page
Dynamic: license
Dynamic: maintainer
Dynamic: maintainer-email
Dynamic: project-url
Dynamic: provides-extra
Dynamic: requires-dist
Dynamic: requires-python
Dynamic: summary
